metabgc/__init__.py
metabgc/metabgc_cmds.py
metabgc/src/__init__.py
metabgc/src/addmetadatatofasta.py
metabgc/src/blastrunlib.py
metabgc/src/createsphmms.py
metabgc/src/evaluate_sphmms.py
metabgc/src/extractfastaseq.py
metabgc/src/hmmerrunlib.py
metabgc/src/hmmrecord.py
metabgc/src/metabgcanalytics.py
metabgc/src/metabgcbuild.py
metabgc/src/metabgccluster.py
metabgc/src/metabgcfindTP.py
metabgc/src/metabgcidentify.py
metabgc/src/metabgcquantify.py
metabgc/src/metabgcsynthesize.py
metabgc/src/producer_consumer.py
metabgc/src/sphmmparser.py
metabgc/src/utils.py
metabgc-2.0.0.dist-info/LICENSE
metabgc-2.0.0.dist-info/METADATA
metabgc-2.0.0.dist-info/WHEEL
metabgc-2.0.0.dist-info/entry_points.txt
metabgc-2.0.0.dist-info/top_level.txt
metabgc-2.0.0.dist-info/RECORD
