Metadata-Version: 2.1
Name: metabgc
Version: 2.0.0
Summary: Metagenomic identifier of Biosynthetic Gene Clusters.
Home-page: https://github.com/donia-lab/MetaBGC
Author: MetaBGC development team.
Author-email: ab50@princeton.edu
License: GNU General Public License v3
Platform: UNKNOWN
Classifier: Programming Language :: Python
Classifier: Programming Language :: Python :: 3
Classifier: Development Status :: 3 - Alpha
Classifier: Intended Audience :: Science/Research
Classifier: Topic :: Scientific/Engineering :: Bio-Informatics
Classifier: License :: OSI Approved :: GNU General Public License v3 or later (GPLv3+)
Classifier: Operating System :: POSIX :: Linux
Requires-Python: >=3.6
Requires-Dist: click
Requires-Dist: numpy
Requires-Dist: matplotlib
Requires-Dist: scipy
Requires-Dist: biopython (<1.78,>=1.72)
Requires-Dist: scikit-learn (>=0.20.1)
Requires-Dist: pandas (>=0.19.2)
Requires-Dist: pytest
